snap_pslg/__init__.py
snap_pslg/bounding_boxes.py
snap_pslg/bvh.py
snap_pslg/helpers.py
snap_pslg/intersections.py
snap_pslg/main.py
snap_pslg/py.typed
snap_pslg/segments_and_pixels.py
snap_pslg/type_hints.py
snap_pslg/view_pslg.py
snap_pslg-0.5.0.dist-info/WHEEL
snap_pslg-0.5.0.dist-info/METADATA
snap_pslg-0.5.0.dist-info/RECORD
