Metadata-Version: 2.4
Name: snap-pslg
Version: 0.5.0
Summary: simplify a pslg with iterated snap rounding
Author: Shay Hill
Author-email: Shay Hill <shay_public@hotmail.com>
License-Expression: MIT
Requires-Python: >=3.10
